python_rust_torch_playground-0.0.1.dist-info/METADATA
python_rust_torch_playground-0.0.1.dist-info/WHEEL
python_rust_torch_playground-0.0.1.dist-info/license_files/LICENSE
python_rust_torch_playground/__init__.py
python_rust_torch_playground/python_rust_torch_playground.cpython-310-darwin.so
python_rust_torch_playground-0.0.1.dist-info/RECORD
