Metadata-Version: 2.3
Name: python-rust-torch-playground
Version: 0.0.1
Classifier: License :: OSI Approved :: MIT License
Classifier: Programming Language :: Rust
Classifier: Programming Language :: Python :: 3.10
Classifier: Programming Language :: Python :: 3.11
Classifier: Programming Language :: Python :: 3.12
Classifier: Programming Language :: Python :: Implementation :: CPython
Classifier: Topic :: Scientific/Engineering :: Artificial Intelligence
Requires-Dist: numpy >=1.26.4
Requires-Dist: torch ==2.2.0
License-File: LICENSE
Summary: A playground for Python, Rust, and PyTorch
Keywords: python,rust,torch,demo
Author: Asher Jingkong Chen
Requires-Python: >=3.10
Project-URL: Homepage, https://github.com/AsherJingkongChen/python-rust-torch-playground/blob/main/README.md
Project-URL: Repository, https://github.com/AsherJingkongChen/python-rust-torch-playground.git
